MANIFEST.in
README.rst
os_admin_networks_python_novaclient_ext.py
setup.py
os_admin_networks_python_novaclient_ext.egg-info/PKG-INFO
os_admin_networks_python_novaclient_ext.egg-info/SOURCES.txt
os_admin_networks_python_novaclient_ext.egg-info/dependency_links.txt
os_admin_networks_python_novaclient_ext.egg-info/requires.txt
os_admin_networks_python_novaclient_ext.egg-info/top_level.txt