Metadata-Version: 1.0
Name: os-admin-networks-python-novaclient-ext
Version: 0.1
Summary: Adds Admin Networks support to python-novaclient
Home-page: https://github.com/cerberus98/os_admin_networks_python_novaclient_ext
Author: Rackspace
Author-email: matt.dietz@rackspace.com
License: Apache License, Version 2.0
Platform: UNKNOWN
Classifier: Development Status :: 3 - Alpha
Classifier: Intended Audience :: Developers
Classifier: Intended Audience :: Information Technology
Classifier: License :: OSI Approved :: Apache Software License
Classifier: Operating System :: OS Independent
Classifier: Programming Language :: Python
